ned/__about__.py
ned/__init__.py
ned/__main__.py
ned/api.py
ned/app.py
ned/config.py
ned/constants.py
ned/session.py
ned/timer.py
ned/utils.py
ned/widgets.py
ned/controllers/__init__.py
ned/controllers/main.py
ned/controllers/preload.py
ned/controllers/setup.py
ned/resources/__init__.py
ned/resources/styles.css
ned/resources/layouts/main.xml
ned/resources/layouts/music_picker.xml
ned/resources/layouts/preload.xml
ned/resources/layouts/setup.xml
ned/spotify/__init__.py
ned/spotify/api_instance.py
ned/spotify/client.py
ned/spotify/scope.py
ned/spotify/session_data.py
ned/spotify/pkce/__init__.py
ned/spotify/pkce/auth.py
ned/spotify/pkce/server.py
ned_client-0.0.2.dist-info/METADATA
ned_client-0.0.2.dist-info/WHEEL
ned_client-0.0.2.dist-info/entry_points.txt
ned_client-0.0.2.dist-info/licenses/LICENSE.txt
ned_client-0.0.2.dist-info/RECORD
