Metadata-Version: 2.4
Name: ned-client
Version: 0.0.2
Summary: A terminal interface for Spotify
Project-URL: Documentation, https://github.com/Jackkillian/ned#readme
Project-URL: Issues, https://github.com/Jackkillian/ned/issues
Project-URL: Source, https://github.com/Jackkillian/ned
Author-email: Jackkillian <jackkillian@tuta.com>
License-Expression: MIT
License-File: LICENSE.txt
Keywords: spotify,tui
Requires-Python: >=3.9
Requires-Dist: cfgsaver
Requires-Dist: modern-urwid>=1.1.3
Requires-Dist: requests
Requires-Dist: urwid
